systembridgecli/__init__.py
systembridgecli/__main__.py
systembridgecli/_version.py
systembridgecli-4.0.6.dist-info/LICENSE
systembridgecli-4.0.6.dist-info/METADATA
systembridgecli-4.0.6.dist-info/WHEEL
systembridgecli-4.0.6.dist-info/top_level.txt
systembridgecli-4.0.6.dist-info/RECORD
