Metadata-Version: 2.1
Name: systembridgecli
Version: 4.0.6
Summary: System Bridge CLI
Home-page: https://github.com/timmo001/system-bridge-cli
Author: Aidan Timson (Timmo)
Author-email: aidan@timmo.dev
License: Apache-2.0
Keywords: system-bridge
Requires-Python: >=3.11
License-File: LICENSE
Requires-Dist: incremental>=24.7.2
Requires-Dist: shellingham==1.5.4
Requires-Dist: systembridgeconnector>=4.0.5
Requires-Dist: systembridgeshared>=4.0.4
Requires-Dist: typer==0.12.3
